[
  {
    "timestamp": "2026-07-12 15:59:36.261805",
    "coins": []
  },
  {
    "timestamp": "2026-07-12 17:10:39.000417",
    "coins": []
  },
  {
    "timestamp": "2026-07-12 19:04:56.150180",
    "coins": []
  },
  {
    "timestamp": "2026-07-12 20:47:01.538236",
    "coins": []
  },
  {
    "timestamp": "2026-07-12 21:49:46.317453",
    "coins": []
  },
  {
    "timestamp": "2026-07-12 22:47:34.140845",
    "coins": []
  },
  {
    "timestamp": "2026-07-12 23:53:27.618460",
    "coins": []
  },
  {
    "timestamp": "2026-07-13 02:43:31.092091",
    "coins": []
  },
  {
    "timestamp": "2026-07-13 06:17:49.871091",
    "coins": []
  },
  {
    "timestamp": "2026-07-13 10:25:28.989055",
    "coins": []
  },
  {
    "timestamp": "2026-07-13 13:22:57.756694",
    "coins": []
  },
  {
    "timestamp": "2026-07-13 16:32:32.818681",
    "coins": []
  },
  {
    "timestamp": "2026-07-13 18:43:00.882502",
    "coins": []
  },
  {
    "timestamp": "2026-07-13 20:14:24.078394",
    "coins": []
  },
  {
    "timestamp": "2026-07-13 21:55:53.182556",
    "coins": []
  },
  {
    "timestamp": "2026-07-13 22:56:03.094567",
    "coins": []
  },
  {
    "timestamp": "2026-07-13 23:54:47.379247",
    "coins": []
  },
  {
    "timestamp": "2026-07-14 02:26:34.742340",
    "coins": []
  },
  {
    "timestamp": "2026-07-14 05:29:42.025560",
    "coins": []
  },
  {
    "timestamp": "2026-07-14 08:03:12.860036",
    "coins": []
  },
  {
    "timestamp": "2026-07-14 10:45:14.944918",
    "coins": []
  },
  {
    "timestamp": "2026-07-14 12:11:25.313335",
    "coins": []
  },
  {
    "timestamp": "2026-07-14 14:50:21.586473",
    "coins": []
  },
  {
    "timestamp": "2026-07-14 16:14:14.489872",
    "coins": []
  },
  {
    "timestamp": "2026-07-14 18:02:20.104103",
    "coins": []
  },
  {
    "timestamp": "2026-07-14 20:10:42.738279",
    "coins": []
  },
  {
    "timestamp": "2026-07-14 21:57:00.593969",
    "coins": []
  },
  {
    "timestamp": "2026-07-14 22:58:57.370282",
    "coins": []
  },
  {
    "timestamp": "2026-07-14 23:59:30.308582",
    "coins": []
  },
  {
    "timestamp": "2026-07-15 03:20:51.146977",
    "coins": []
  },
  {
    "timestamp": "2026-07-15 06:13:02.147896",
    "coins": []
  },
  {
    "timestamp": "2026-07-15 09:08:53.864115",
    "coins": []
  },
  {
    "timestamp": "2026-07-15 11:27:53.254303",
    "coins": []
  },
  {
    "timestamp": "2026-07-15 13:41:50.052681",
    "coins": []
  },
  {
    "timestamp": "2026-07-15 15:25:42.085125",
    "coins": []
  },
  {
    "timestamp": "2026-07-15 17:16:39.650527",
    "coins": []
  },
  {
    "timestamp": "2026-07-15 19:09:25.801117",
    "coins": []
  },
  {
    "timestamp": "2026-07-15 20:59:33.230112",
    "coins": []
  },
  {
    "timestamp": "2026-07-15 22:09:11.846556",
    "coins": []
  },
  {
    "timestamp": "2026-07-15 23:57:18.965089",
    "coins": []
  },
  {
    "timestamp": "2026-07-16 02:54:06.640106",
    "coins": []
  },
  {
    "timestamp": "2026-07-16 05:40:09.709486",
    "coins": []
  },
  {
    "timestamp": "2026-07-16 08:11:56.253711",
    "coins": []
  },
  {
    "timestamp": "2026-07-16 10:59:17.957575",
    "coins": []
  },
  {
    "timestamp": "2026-07-16 12:25:55.824946",
    "coins": []
  },
  {
    "timestamp": "2026-07-16 15:01:30.387727",
    "coins": []
  },
  {
    "timestamp": "2026-07-16 17:14:30.692064",
    "coins": []
  },
  {
    "timestamp": "2026-07-16 19:08:59.689753",
    "coins": []
  },
  {
    "timestamp": "2026-07-16 20:57:05.888562",
    "coins": []
  },
  {
    "timestamp": "2026-07-16 22:05:34.523758",
    "coins": []
  }
]